pyramid_tm/__init__.py
pyramid_tm-2.5.dist-info/LICENSE.txt
pyramid_tm-2.5.dist-info/METADATA
pyramid_tm-2.5.dist-info/WHEEL
pyramid_tm-2.5.dist-info/top_level.txt
pyramid_tm-2.5.dist-info/RECORD
