Metadata-Version: 2.1
Name: pyramid-tm
Version: 2.5
Summary: A package which allows Pyramid requests to join the active transaction
Home-page: https://github.com/Pylons/pyramid_tm
Author: Rocky Burt, Chris McDonough
Author-email: pylons-discuss@googlegroups.com
Maintainer: Pylons Project
Maintainer-email: pylons-discuss@googlegroups.com
License: BSD-derived (Repoze)
Project-URL: Documentation, https://docs.pylonsproject.org/projects/pyramid-tm/en/latest/index.html
Project-URL: Changelog, https://docs.pylonsproject.org/projects/pyramid-tm/en/latest/changes.html
Project-URL: Issue Tracker, https://github.com/Pylons/pyramid_tm/issues
Keywords: wsgi pylons pyramid transaction
Platform: UNKNOWN
Classifier: Development Status :: 6 - Mature
Classifier: Intended Audience :: Developers
Classifier: Programming Language :: Python
Classifier: Programming Language :: Python :: 3
Classifier: Programming Language :: Python :: 3.7
Classifier: Programming Language :: Python :: 3.8
Classifier: Programming Language :: Python :: 3.9
Classifier: Programming Language :: Python :: 3.10
Classifier: Programming Language :: Python :: Implementation :: CPython
Classifier: Programming Language :: Python :: Implementation :: PyPy
Classifier: Operating System :: OS Independent
Classifier: Framework :: Pyramid
Classifier: License :: Repoze Public License
Requires-Python: >=3.7
Provides-Extra: testing
Provides-Extra: docs
License-File: LICENSE.txt
